socketapi/__init__.py
socketapi/annotations.py
socketapi/handlers.py
socketapi/main.py
socketapi/manager.py
socketapi/py.typed
socketapi/router.py
socketapi/testclient.py
socketapi/validation.py
socketapi-0.2.0.dist-info/WHEEL
socketapi-0.2.0.dist-info/METADATA
socketapi-0.2.0.dist-info/RECORD
