Metadata-Version: 2.4
Name: socketapi
Version: 0.2.0
Summary: SocketAPI is a lightweight Python framework for real-time WebSocket APIs, using a single multiplexed connection with endpoint-like actions and channel subscriptions.
Author: SpaceShaman
Author-email: SpaceShaman <spaceshaman@tuta.io>
License-Expression: MIT
Classifier: Framework :: Pydantic
Classifier: Framework :: Pydantic :: 2
Classifier: Programming Language :: Python :: 3
Classifier: Programming Language :: Python :: 3.11
Classifier: Programming Language :: Python :: 3.12
Classifier: Programming Language :: Python :: 3.13
Classifier: Programming Language :: Python :: 3.14
Classifier: Programming Language :: Python :: Implementation :: CPython
Classifier: License :: OSI Approved :: MIT License
Requires-Dist: httpx>=0.28.1
Requires-Dist: pydantic>=2.12.5
Requires-Dist: starlette>=0.50.0
Requires-Python: >=3.11
